npdep_receiver/__init__.py
npdep_receiver/__main__.py
npdep_receiver/args/Args.py
npdep_receiver/args/__init__.py
npdep_receiver/output/Output.py
npdep_receiver/output/__init__.py
npdep_receiver/receiver/__init__.py
npdep_receiver/receiver/base/Receiver.py
npdep_receiver/receiver/base/__init__.py
npdep_receiver/receiver/module/__init__.py
npdep_receiver/receiver/module/dep/DepMessageProcessor.py
npdep_receiver/receiver/module/dep/DepReceiver.py
npdep_receiver/receiver/module/dep/__init__.py
npdep_receiver/receiver/module/http_dep_tunnel/HttpDepMessageProcessor.py
npdep_receiver/receiver/module/http_dep_tunnel/HttpDepReceiver.py
npdep_receiver/receiver/module/http_dep_tunnel/__init__.py
npdep_receiver/receiver/module/icmp_echo/IcmpEchoReceiver.py
npdep_receiver/receiver/module/icmp_echo/__init__.py
npdep_receiver/util/Util.py
npdep_receiver/util/__init__.py
npdep_receiver-0.1.0.dist-info/METADATA
npdep_receiver-0.1.0.dist-info/WHEEL
npdep_receiver-0.1.0.dist-info/entry_points.txt
npdep_receiver-0.1.0.dist-info/top_level.txt
npdep_receiver-0.1.0.dist-info/RECORD
