Metadata-Version: 2.1
Name: npdep_receiver
Version: 0.1.0
Summary: Receiver Modules for Network Protocol Data Exfiltration Project Server
Home-page: https://github.com/npdep/npdep-receiver
Author: npdep
Classifier: Operating System :: OS Independent 
Classifier: Programming Language :: Python :: 3 
Requires-Dist: dep-common
Requires-Dist: dep-reader
